dmarc_reports/__init__.py
dmarc_reports/classes.py
dmarc_reports/exceptions.py
dmarc_reports-0.0.2.dist-info/LICENSE
dmarc_reports-0.0.2.dist-info/METADATA
dmarc_reports-0.0.2.dist-info/WHEEL
dmarc_reports-0.0.2.dist-info/top_level.txt
dmarc_reports-0.0.2.dist-info/RECORD
