Metadata-Version: 2.1
Name: dmarc-reports
Version: 0.0.2
Summary: The Python package for parsing, validation and storage of DMARC reports.
Home-page: UNKNOWN
Author: Rui Antunes
Author-email: 
License: UNKNOWN
Project-URL: GitHub, https://github.com/rui-antunes/dmarc-reports/
Platform: UNKNOWN
Classifier: Programming Language :: Python :: 3
Classifier: License :: OSI Approved :: MIT License
Classifier: Operating System :: OS Independent
Requires-Python: >=3.6
License-File: LICENSE
